mo_imports/__init__.py
mo_imports-7.685.25166.dist-info/licenses/LICENSE
mo_imports-7.685.25166.dist-info/METADATA
mo_imports-7.685.25166.dist-info/WHEEL
mo_imports-7.685.25166.dist-info/top_level.txt
mo_imports-7.685.25166.dist-info/RECORD
